distributed_logger/__init__.py
distributed_logger/loggers/__init__.py
distributed_logger/loggers/factory.py
distributed_logger/loggers/logger.py
distributed_logger/loggers/tests/__init__.py
distributed_logger/loggers/tests/logger_test.py
distributed_logger/middleware/__init__.py
distributed_logger/middleware/log_middleware.py
distributed_logger/models/__init__.py
distributed_logger/models/config.py
distributed_logger/models/log.py
distributed_logger-0.1.13.dist-info/METADATA
distributed_logger-0.1.13.dist-info/WHEEL
distributed_logger-0.1.13.dist-info/top_level.txt
distributed_logger-0.1.13.dist-info/RECORD
