Metadata-Version: 2.4
Name: distributed-logger
Version: 0.1.13
Summary: A lightweight logging system with Kafka support for auditing and debugging
Home-page: https://github.com/arjun-navya/distributed-logger
Author: Arjun Navya
Author-email: arjun.dahal@navyaadvisors.com
Classifier: Development Status :: 3 - Alpha
Classifier: Intended Audience :: Developers
Classifier: License :: OSI Approved :: MIT License
Classifier: Operating System :: OS Independent
Classifier: Programming Language :: Python :: 3
Classifier: Programming Language :: Python :: 3.9
Classifier: Programming Language :: Python :: 3.10
Classifier: Programming Language :: Python :: 3.11
Classifier: Programming Language :: Python :: 3.12
Classifier: Topic :: System :: Logging
Requires-Python: >=3.9
Requires-Dist: kafka-python>=2.2.12
Requires-Dist: python-json-logger>=3.3.0
Requires-Dist: asgiref<3.8.0,>=3.4.1
Requires-Dist: Django<4.1.0,>=4.0.0
Requires-Dist: sqlparse<0.5.0,>=0.2.2
Requires-Dist: typing_extensions>=4.14.0
Provides-Extra: dev
Requires-Dist: pytest>=6.0; extra == "dev"
Requires-Dist: pytest-cov>=2.0; extra == "dev"
Requires-Dist: black>=21.0; extra == "dev"
Requires-Dist: flake8>=3.8; extra == "dev"
Requires-Dist: mypy>=0.800; extra == "dev"
Dynamic: author
Dynamic: author-email
Dynamic: classifier
Dynamic: description
Dynamic: description-content-type
Dynamic: home-page
Dynamic: provides-extra
Dynamic: requires-dist
Dynamic: requires-python
Dynamic: summary
